{
  "main": {
    "id": "be0dc1b3e6ef7bf5",
    "type": "split",
    "children": [
      {
        "id": "96318e3d46ec7b2f",
        "type": "tabs",
        "children": [
          {
            "id": "226d0582c1058fbc",
            "type": "leaf",
            "state": {
              "type": "markdown",
              "state": {
                "file": "MATH 3130/Transformations.md",
                "mode": "source",
                "source": false
              }
            }
          },
          {
            "id": "5e717785ab3fb9fc",
            "type": "leaf",
            "state": {
              "type": "markdown",
              "state": {
                "file": "CIS 1210/Heaps.md",
                "mode": "source",
                "source": false
              }
            }
          },
          {
            "id": "4b71b55ecaf25611",
            "type": "leaf",
            "state": {
              "type": "markdown",
              "state": {
                "file": "CIS 1210/Huffman Encoding.md",
                "mode": "source",
                "source": false
              }
            }
          },
          {
            "id": "037f9467748054dd",
            "type": "leaf",
            "state": {
              "type": "markdown",
              "state": {
                "file": "CIS 1210/Graph Traversals.md",
                "mode": "source",
                "source": false
              }
            }
          },
          {
            "id": "8a1923623753a435",
            "type": "leaf",
            "state": {
              "type": "markdown",
              "state": {
                "file": "CIS 1210/Bipartiteness.md",
                "mode": "source",
                "source": false
              }
            }
          },
          {
            "id": "28de5e5540c7c5a4",
            "type": "leaf",
            "state": {
              "type": "markdown",
              "state": {
                "file": "CIS 1210/Bipartiteness.md",
                "mode": "source",
                "source": false
              }
            }
          },
          {
            "id": "288161a18e43aabf",
            "type": "leaf",
            "state": {
              "type": "markdown",
              "state": {
                "file": "CIS 1210/Hashing.md",
                "mode": "source",
                "source": false
              }
            }
          },
          {
            "id": "e848969f3c2d1609",
            "type": "leaf",
            "state": {
              "type": "markdown",
              "state": {
                "file": "MATH 3130/Transformations.md",
                "mode": "source",
                "source": false
              }
            }
          },
          {
            "id": "f49f72cbe3278b71",
            "type": "leaf",
            "state": {
              "type": "markdown",
              "state": {
                "file": "CHIN 1140.md",
                "mode": "source",
                "source": false
              }
            }
          }
        ],
        "currentTab": 8
      }
    ],
    "direction": "vertical"
  },
  "left": {
    "id": "4e15a431815b2bf0",
    "type": "split",
    "children": [
      {
        "id": "7a1ed35edeeecacf",
        "type": "tabs",
        "children": [
          {
            "id": "238fc620f3a7044a",
            "type": "leaf",
            "state": {
              "type": "file-explorer",
              "state": {
                "sortOrder": "alphabetical"
              }
            }
          },
          {
            "id": "6502dd2f1c833d14",
            "type": "leaf",
            "state": {
              "type": "search",
              "state": {
                "query": "",
                "matchingCase": false,
                "explainSearch": false,
                "collapseAll": false,
                "extraContext": false,
                "sortOrder": "alphabetical"
              }
            }
          },
          {
            "id": "0ef9afc6229fcb04",
            "type": "leaf",
            "state": {
              "type": "starred",
              "state": {}
            }
          }
        ]
      }
    ],
    "direction": "horizontal",
    "width": 300
  },
  "right": {
    "id": "256209e4c2e36f33",
    "type": "split",
    "children": [
      {
        "id": "2aeaa33ae75b0916",
        "type": "tabs",
        "children": [
          {
            "id": "dd9a7c4ccda11998",
            "type": "leaf",
            "state": {
              "type": "backlink",
              "state": {
                "file": "CHIN 1140.md",
                "collapseAll": false,
                "extraContext": false,
                "sortOrder": "alphabetical",
                "showSearch": false,
                "searchQuery": "",
                "backlinkCollapsed": false,
                "unlinkedCollapsed": true
              }
            }
          },
          {
            "id": "799805fb0e2a7076",
            "type": "leaf",
            "state": {
              "type": "outgoing-link",
              "state": {
                "file": "CHIN 1140.md",
                "linksCollapsed": false,
                "unlinkedCollapsed": true
              }
            }
          },
          {
            "id": "a0b8b96dc1b51f9a",
            "type": "leaf",
            "state": {
              "type": "tag",
              "state": {
                "sortOrder": "frequency",
                "useHierarchy": true
              }
            }
          },
          {
            "id": "5e1393ba38d905a9",
            "type": "leaf",
            "state": {
              "type": "outline",
              "state": {
                "file": "CHIN 1140.md"
              }
            }
          }
        ]
      }
    ],
    "direction": "horizontal",
    "width": 300,
    "collapsed": true
  },
  "left-ribbon": {
    "hiddenItems": {
      "switcher:Open quick switcher": false,
      "graph:Open graph view": false,
      "canvas:Create new canvas": false,
      "daily-notes:Open today's daily note": false,
      "templates:Insert template": false,
      "command-palette:Open command palette": false
    }
  },
  "active": "238fc620f3a7044a",
  "lastOpenFiles": [
    "MATH 3130/Transformations.md",
    "CHIN 1140.md",
    "CIS 1210/Midterm 2 Review.md",
    "CIS 1210/Hashing.md",
    "CIS 1210/Directed Acyclic Graphs (DAGs).md",
    "Glossary/Computer Science.md",
    "Glossary",
    "CIS 1210/Strongly Connected Components.md",
    "CIS 1210/Shortest Path.md",
    "CIS 1210/Minimum Spanning Trees (MSTs).md",
    "CIS 1210/Bipartiteness.md",
    "CIS 1210/Union Find.md",
    "README.md",
    "CIS 1210/Graph Traversals.md",
    "CIS 1210/Huffman Encoding.md",
    "CIS 1210/Heaps.md",
    "LING 2300/Rule Ordering.md",
    "LING 2300/Distributions.md",
    "Rule Ordering.md",
    "MATH 3130",
    "LING 2300",
    "LING 5250/The DFT.md",
    "LING 5250/Signals.md",
    "LING 5250/Untitled.md",
    "LING 5250",
    "CIS 1210"
  ]
}